{
  "year": "1999",
  "awards": "2 wins & 5 nominations total",
  "rated": "R",
  "released": "10 Mar 2000",
  "runtime": "133 min",
  "genre": "Mystery, Thriller",
  "director": "Roman Polanski",
  "writer": "Arturo Pérez-Reverte, John Brownjohn, Enrique Urbizu",
  "actors": "Johnny Depp, Frank Langella, Lena Olin",
  "plot": "In New York, the money-driven dealer Dean Corso is a rare-books expert and partner of Bernie, who owns a bookstore. He is contacted by the renowned collector of books about the devil Boris Balkan, who has just acquired the rare The Nine Gates of the Kingdom of Shadows from the collector Andrew Telfer, to verify whether his book is authentic or a forgery. Balkan explains that the book was written by the writer Aristide Torchia, in 1666, with Lucifer and he was burned at the stake with his entire work. There are only three exemplars of The Nine Gates and in accordance with the legend, its nine engravings form a riddle to conjure the devil. The skeptical Corso accepts the assignment and has to fly to Sintra, Portugal, and Paris, France, to contact the owners Victor Fargas and Baroness Kessler and find the genuine exemplar for Balkan. Meanwhile, he asks Bernie to hide the rare book. Before traveling to Europe, the widow Liana Telfer wants to retrieve the book and has sex with Corso, but he does not accept her offer. When Corso returns to Bernie's bookstore, he finds his friend murdered in the same position of an engraving. Corso travels to Toledo, Spain, to meet the Ceniza twin brothers and learn more about The Nine Gates. During his journey in Europe, Corso is pursued by Liana and her bodyguard, who belong to the sect The Order of the Silver Serpents, and is protected by a mysterious Girl with supernatural powers. Meanwhile, the owners of the two other exemplars of The Nine Gates are murdered. Corso becomes obsessed with the book and discloses the truth about it.",
  "language": "English, French, Latin, Portuguese, Spanish",
  "country": "France, Spain, United States",
  "metascore": "44",
  "imdb_rating": "6.7",
  "imdb_votes": "208,262",
  "box_office": "$18,661,336",
  "dvd": "N/A",
  "ratings": [
    {
      "source": "Internet Movie Database",
      "value": "6.7/10"
    },
    {
      "source": "Rotten Tomatoes",
      "value": "44%",
      "link": "https://www.rottentomatoes.com/search?search=The+Ninth+Gate"
    },
    {
      "source": "Metacritic",
      "value": "44/100",
      "link": "https://www.metacritic.com/search/The+Ninth+Gate/"
    }
  ],
  "links": {
    "imdb": "https://www.imdb.com/title/tt0142688/",
    "imdb_fullcredits": "https://www.imdb.com/title/tt0142688/fullcredits",
    "tmdb": "https://www.themoviedb.org/movie/622"
  }
}