{
  "year": "1996",
  "awards": "Won 1 Oscar. 35 wins & 35 nominations total",
  "rated": "PG-13",
  "released": "03 Jul 1996",
  "runtime": "145 min",
  "genre": "Action, Adventure, Sci-Fi",
  "director": "Roland Emmerich",
  "writer": "Dean Devlin, Roland Emmerich",
  "actors": "Will Smith, Bill Pullman, Jeff Goldblum",
  "plot": "On July 2nd, communications systems worldwide are sent into chaos by a strange atmospheric interference. It is soon learned by the military that a number of enormous objects are on a collision course with Earth. At first thought to be meteors, they are later revealed to be gigantic spacecraft, piloted by a mysterious alien species. After attempts to communicate with the aliens go nowhere, David Levinson, an ex-scientist turned cable technician, discovers that the aliens are going to attack major points around the globe in less than a day. On July 3rd, the aliens all but obliterate New York, Los Angeles and Washington, as well as Paris, London, Houston and Moscow. The survivors set out in convoys towards Area 51, a strange government testing ground where it is rumored the military has a captured alien spacecraft of their own. The survivors devise a plan to fight back against the enslaving aliens, and July 4th becomes the day humanity will fight for its freedom. July 4th is their Independence Day...",
  "language": "English",
  "country": "United States",
  "metascore": "59",
  "imdb_rating": "7.0",
  "imdb_votes": "642,170",
  "box_office": "$306,169,268",
  "dvd": "N/A",
  "ratings": [
    {
      "source": "Internet Movie Database",
      "value": "7.0/10"
    },
    {
      "source": "Rotten Tomatoes",
      "value": "69%",
      "link": "https://www.rottentomatoes.com/search?search=Independence+Day"
    },
    {
      "source": "Metacritic",
      "value": "59/100",
      "link": "https://www.metacritic.com/search/Independence+Day/"
    }
  ],
  "links": {
    "imdb": "https://www.imdb.com/title/tt0116629/",
    "imdb_fullcredits": "https://www.imdb.com/title/tt0116629/fullcredits",
    "tmdb": "https://www.themoviedb.org/movie/602"
  }
}